stringmod/__init__.py
stringmod/main.py
stringmod-1.1.0.dist-info/METADATA
stringmod-1.1.0.dist-info/WHEEL
stringmod-1.1.0.dist-info/top_level.txt
stringmod-1.1.0.dist-info/RECORD
