Metadata-Version: 2.1
Name: stringmod
Version: 1.1.0
Summary: A Python package for basic string usage
Home-page: https://github.com/cyberzendev/stringmod
Author: CyberZen
Author-email: cyberzendev@gmail.com
Classifier: Development Status :: 5 - Production/Stable
Classifier: Intended Audience :: Developers
Classifier: License :: OSI Approved :: MIT License
Classifier: Programming Language :: Python
Classifier: Programming Language :: Python :: 3
Classifier: Programming Language :: Python :: 3.6
Classifier: Programming Language :: Python :: 3.7
Classifier: Programming Language :: Python :: 3.8
Classifier: Programming Language :: Python :: 3.9
